fractlang/__init__.py
fractlang/frxparser.py
fractlang-0.1.29.dist-info/METADATA
fractlang-0.1.29.dist-info/WHEEL
fractlang-0.1.29.dist-info/entry_points.txt
fractlang-0.1.29.dist-info/top_level.txt
fractlang-0.1.29.dist-info/RECORD
